[
  {
    "name": "便利蜂卫生巾、湿巾、口罩、抽纸、饼干、香肠、咖啡、牛奶",
    "detail": "具体商品点击详情",
    "delivery": 30,
    "keywords": [
      "卫生巾",
      "湿巾",
      "口罩",
      "抽纸",
      "饼干",
      "香肠",
      "咖啡",
      "牛奶"
    ],
    "price": 0,
    "unit": "箱",
    "image": "/image/0408/0000.jpeg",
    "contacts": [
      {
        "name": "修女士",
        "phone": "13671845251"
      }
    ]
  },
  {
    "name": "天使之橙居家套餐",
    "detail": "猪肉2斤+土鸡蛋3斤+土豆2斤+胡萝卜1斤+西红柿2斤+包菜1棵+芹菜2斤+洋葱3个+大白菜1棵+鲜橙10个",
    "delivery": 30,
    "keywords": ["猪肉", "鸡蛋", "蔬菜", "水果"],
    "price": 188,
    "unit": "套",
    "image": "/image/0408/0001.jpeg",
    "contacts": [
      {
        "name": "客服热线",
        "phone": "4000 365 517"
      },
      {
        "name": "团购联系人 方青",
        "phone": "13801853078"
      }
    ]
  },
  {
    "name": "DOLE都乐阳光果蔬:菠萝、香蕉、啤梨、番茄、牛油果、玉米粒",
    "detail": "具体商品点击详情",
    "delivery": 50,
    "keywords": ["主食", "蔬菜", "水果"],
    "price": 0,
    "unit": "箱",
    "image": "/image/0408/0002.jpeg",
    "contacts": []
  },
  {
    "name": "大山合: 79元干菜菌菇套餐(1150克)、69元杂稂菌菇组合(980克)",
    "detail": "具体商品点击详情",
    "delivery": "40/60",
    "keywords": ["主食", "干菜", "菌菇"],
    "price": "79/69",
    "unit": "份",
    "image": "/image/0408/0003.jpeg",
    "contacts": [
      {
        "name": "松江、青浦 | 卢敏",
        "phone": "13611939680"
      },
      {
        "name": "闵行、嘉定、宝山 | 善文",
        "phone": "15618704058"
      },
      {
        "name": "奉贤、金山、浦东新区 | 元嵩",
        "phone": "18121163729"
      }
    ]
  },
  {
    "name": "上海闽龙实业有限公司: 橙子、套餐A/B",
    "detail": "具体商品点击详情",
    "delivery": "50",
    "keywords": ["蔬菜", "鸡蛋", "豆制品", "食用油", "干果", "咖啡"],
    "unit": "单",
    "image": "/image/0408/0004.png",
    "contacts": [
      {
        "name": "范女士",
        "phone": "15221678767"
      },
      {
        "name": "唐女士",
        "phone": "13818611658"
      },
      {
        "name": "谢女士",
        "phone": "15901647541"
      }
    ]
  },
  {
    "name": "光明: 奶粉、益生菌粉",
    "detail": "具体商品点击详情",
    "delivery": 3000,
    "keywords": ["奶粉", "益生菌粉"],
    "unit": "元",
    "image": "/image/0408/0005.jpeg",
    "contacts": [
      { "name": "杨浦、宝山 | 瞿鹏", "phone": "13761122656" },
      { "name": "松江、青浦 | 曹木", "phone": "13311828670" },
      { "name": "静安（原闸北）、宝山 | 王卫东", "phone": "13601635801" },
      { "name": "虹口、黄浦 | 王鸣", "phone": "13817070260" },
      { "name": "奉贤、南汇、金山、崇明 | 陈杰", "phone": "15021450977" },
      { "name": "静安、长宁 | 黄剑", "phone": "13817369750" },
      { "name": "黄浦、浦东新区 | 江泓波", "phone": "13585991128" },
      { "name": "闵行、徐汇 | 丁亚香", "phone": "13564887907" },
      { "name": "普陀、嘉定 | 周赟", "phone": "15000843036" },
      { "name": "闵行、松江 | 李云峰", "phone": "13901606761" },
      { "name": "全市协调 | 杨威", "phone": "13966327680" }
    ]
  },
  {
    "name": "飞鹤: 奶粉",
    "detail": "具体商品点击详情",
    "delivery": 1,
    "keywords": ["奶粉"],
    "unit": "箱",
    "image": "/image/0408/0006.jpeg"
  },
  {
    "name": "惠氏: 奶粉",
    "detail": "具体商品点击详情",
    "delivery": 1,
    "keywords": ["奶粉"],
    "unit": "箱",
    "image": "/image/0408/0007.png",
    "contacts": [{ "name": "客服热线", "phone": "400 770 6666" }]
  },
  {
    "name": "雅培: 奶粉",
    "detail": "具体商品点击详情",
    "keywords": ["奶粉"],
    "image": "/image/0408/0008.jpeg",
    "contacts": [{ "name": "客服热线", "phone": "400 820 6111" }]
  },
  {
    "name": "蒙牛阿尔乐: 奶粉",
    "detail": "具体商品点击详情",
    "delivery": 1,
    "keywords": ["奶粉"],
    "unit": "箱",
    "image": "/image/0408/0009.jpeg"
  },
  {
    "name": "蒙牛: 奶粉",
    "detail": "具体商品点击详情",
    "delivery": 400,
    "keywords": ["奶粉"],
    "unit": "元",
    "image": "/image/0408/0010.jpeg"
  },
  {
    "name": "蒙牛哺育恩: 奶粉",
    "detail": "具体商品点击详情",
    "delivery": 2,
    "keywords": ["奶粉"],
    "unit": "听",
    "image": "/image/0408/0011.jpeg"
  },
  {
    "name": "伊利金领冠: 奶粉",
    "detail": "具体商品点击详情",
    "delivery": 1,
    "keywords": ["奶粉"],
    "unit": "箱",
    "image": "/image/0408/0012.jpeg"
  },
  {
    "name": "贝拉米: 儿童口粮套餐",
    "detail": "具体商品点击详情",
    "delivery": 1,
    "keywords": ["儿童口粮"],
    "unit": "单",
    "image": "/image/0408/0013.jpeg"
  },
  {
    "name": "美素佳儿: 奶粉",
    "detail": "具体商品点击详情",
    "delivery": 1,
    "keywords": ["奶粉"],
    "unit": "箱",
    "image": "/image/0408/0014.jpeg",
    "contacts": [{ "name": "客服热线", "phone": "400 820 2775" }]
  },
  {
    "name": "美团: 母婴用品公益专车",
    "detail": "美团闪购在市政府疫情物资保障专班、市妇联的关心指导下，已经推进了一部分母婴商家恢复线上运营。对于奶粉、纸尿裤等母婴类“刚需”商品的保障问题，如果母婴用户有应急需求，可以打开美团或美团外卖APP，在首页进入“应急帮手”界面，点击“去填写需求”按钮，按照操作提示填写详细的个人信息和需求后，会得到高优先级响应。",
    "keywords": [],
    "image": "/image/0408/0015.jpeg"
  },
  {
    "name": "达能: 奶粉",
    "detail": "具体商品点击详情",
    "delivery": 1,
    "keywords": ["奶粉"],
    "unit": "箱",
    "image": "/image/0408/0016.jpeg"
  },
  {
    "name": "美赞臣: 奶粉",
    "detail": "具体商品点击详情",
    "delivery": 6,
    "keywords": ["奶粉"],
    "unit": "箱",
    "image": "/image/0408/0017.jpeg"
  },
  {
    "name": "君乐宝: 奶粉",
    "detail": "具体商品点击详情",
    "delivery": 1,
    "keywords": ["奶粉"],
    "unit": "箱",
    "image": "/image/0408/0018.jpeg",
    "contacts": [{ "name": "客服热线", "phone": "400 600 6611" }]
  },
  {
    "name": "中国农垦控股上海有限公司: 牛奶、奶粉、果泥、力保健功能饮料、大米、橄榄油、葡萄籽油",
    "detail": "具体商品点击详情",
    "keywords": ["奶粉", "牛奶", "主食", "食用油"],
    "image": "/image/0408/0019.png"
  },
  {
    "name": "好孩子: 纸尿裤、拉拉裤、湿巾、棉柔巾、防护套餐",
    "detail": "具体商品点击详情",
    "keywords": ["母婴用品", "湿巾", "棉柔巾"],
    "image": "/image/0408/0020.jpeg"
  },
  {
    "name": "好熟悉: 咖啡",
    "detail": "具体商品点击详情",
    "keywords": ["咖啡"],
    "delivery": 3000,
    "unit": "元",
    "image": "/image/0408/0021.png"
  },
  {
    "name": "纽仕兰: 牛奶",
    "detail": "具体商品点击详情",
    "keywords": ["牛奶"],
    "delivery": 50,
    "unit": "箱",
    "image": "/image/0408/0022.jpeg"
  },
  {
    "name": "光明: 牛奶保质期6个月",
    "detail": "具体商品点击详情",
    "keywords": ["牛奶"],
    "delivery": 60,
    "unit": "提",
    "image": "/image/0408/0023.jpeg"
  },
  {
    "name": "光明: 牛奶保质期7天",
    "detail": "具体商品点击详情",
    "keywords": ["牛奶"],
    "delivery": 200,
    "unit": "份",
    "image": "/image/0408/0024.jpeg"
  },
  {
    "name": "蒙牛: 牛奶保质期6个月",
    "detail": "具体商品点击详情",
    "keywords": ["牛奶"],
    "delivery": 50,
    "unit": "提",
    "image": "/image/0408/0025.jpeg"
  },
  {
    "name": "蒙牛: 酸奶",
    "detail": "具体商品点击详情",
    "keywords": ["牛奶"],
    "delivery": 800,
    "unit": "元",
    "image": "/image/0408/0026.jpeg"
  },
  {
    "name": "伊利: 牛奶",
    "detail": "具体商品点击详情",
    "keywords": ["牛奶"],
    "delivery": 50,
    "unit": "提",
    "image": "/image/0408/0027.jpeg"
  },
  {
    "name": "伊利: 牛奶保质期15天",
    "detail": "具体商品点击详情",
    "keywords": ["牛奶"],
    "delivery": 3000,
    "unit": "元",
    "image": "/image/0408/0028.jpeg"
  },
  {
    "name": "君乐宝: 鲜奶保质期19-21天、酸奶保质期21天、常温酸奶保质期180天",
    "detail": "具体商品点击详情",
    "keywords": ["牛奶"],
    "delivery": 3000,
    "unit": "元",
    "image": "/image/0408/0029.jpeg"
  }
]
